{
  "originalTitle": "1994! - 09.04.2010 - Cambridge - MA - USA - The Harvard Advocate",
  "created": 1704067200,
  "lastUpdated": 1752181957,
  "bands": [
    "1994!"
  ],
  "startDate": {
    "day": "09",
    "month": "04",
    "year": "2010"
  },
  "startDateUnix": 1270771200,
  "endDate": {
    "day": "09",
    "month": "04",
    "year": "2010"
  },
  "endDateUnix": 1270771200,
  "location": {
    "city": "Cambridge",
    "state": "MA",
    "country": "USA",
    "venue": "The Harvard Advocate",
    "event": ""
  },
  "tvChannel": "",
  "showName": "",
  "source": "",
  "category": [
    "video"
  ],
  "master": false,
  "public": true,
  "ownIdentifier": "HDD#O",
  "tradeLabel": "",
  "authoredBy": "",
  "transferredBy": "",
  "notes": "dyinghorse release.",
  "tapers": [],
  "specs": {
    "media": [
      {
        "type": "DVD-5",
        "size": 1.39,
        "unit": "Gb"
      }
    ],
    "chapters": false,
    "menu": false,
    "length": 1295,
    "video": [
      {
        "tvFormat": "NTSC",
        "ratio": "16:9",
        "resolution": "720x480",
        "bitrateType": "VBR",
        "bitrateKbps": null,
        "fps": "",
        "standard": "",
        "codec": "",
        "letterboxed": true
      }
    ],
    "audio": [
      {
        "language": "en",
        "codec": "AC3",
        "rateHz": null,
        "bitrateKbps": null,
        "channels": 2
      }
    ],
    "sourceDetail": {
      "recordingType": "AMT",
      "sourceMediaType": "",
      "finalMediaType": "",
      "fileFormat": "DVD"
    }
  },
  "relatedShows": [],
  "childOf": "",
  "images": [
    {
      "folder": "33",
      "filename": "99913640.jpg",
      "externalId": "1-amZz4ElSAeX67szOlHbCnCD0jWzewaK"
    },
    {
      "folder": "33",
      "filename": "31021873.jpg",
      "externalId": "1hXO4vzDBFHuCo7cOD4_QT_CQA81BoYq8"
    },
    {
      "folder": "33",
      "filename": "94556004.jpg",
      "externalId": "194M_61WvpLX_53xQh0lMkJi52yltCELp"
    },
    {
      "folder": "33",
      "filename": "46461563.jpg",
      "externalId": "11WopSplYUmCwoXNnK-I-wYpwPNr7AuUJ"
    }
  ],
  "setlist": []
}