{
  "originalTitle": "Guano Apes - 14.05.2012 - Moscow - Russia - Milk Club",
  "created": 1704067200,
  "lastUpdated": 1752181957,
  "bands": [
    "Guano Apes"
  ],
  "startDate": {
    "day": "14",
    "month": "05",
    "year": "2012"
  },
  "startDateUnix": 1336953600,
  "endDate": {
    "day": "14",
    "month": "05",
    "year": "2012"
  },
  "endDateUnix": 1336953600,
  "location": {
    "city": "Moscow",
    "state": "",
    "country": "Russia",
    "venue": "Milk Club",
    "event": ""
  },
  "tvChannel": "",
  "showName": "",
  "source": "",
  "category": [
    "video"
  ],
  "master": false,
  "public": true,
  "ownIdentifier": "HDD#D",
  "tradeLabel": "",
  "authoredBy": "",
  "transferredBy": "",
  "notes": "",
  "tapers": [
    "psinka"
  ],
  "specs": {
    "media": [
      {
        "type": "DVD-5",
        "size": 4.47,
        "unit": "Gb"
      }
    ],
    "chapters": false,
    "menu": false,
    "length": 5348,
    "video": [
      {
        "tvFormat": "",
        "ratio": "",
        "resolution": "1280x720",
        "bitrateType": "",
        "bitrateKbps": null,
        "fps": "25",
        "standard": "MPEG4",
        "codec": "H264",
        "letterboxed": false
      }
    ],
    "audio": [
      {
        "language": "",
        "codec": "AAC",
        "rateHz": 44100,
        "bitrateKbps": null,
        "channels": 2
      }
    ],
    "sourceDetail": {
      "recordingType": "AMT",
      "sourceMediaType": "HD",
      "finalMediaType": "",
      "fileFormat": "MKV"
    }
  },
  "relatedShows": [],
  "childOf": "",
  "images": [
    {
      "folder": "45",
      "filename": "57616019.jpg",
      "externalId": "1QF0Ko7j46AJCwIJ-xQtL6eYaJkCIfACO"
    },
    {
      "folder": "45",
      "filename": "50765346.jpg",
      "externalId": "1EI1_V4rbhmqZLyVBG7Km9O2XfZGlDANm"
    },
    {
      "folder": "45",
      "filename": "75401817.jpg",
      "externalId": "14ufHlwUwAPaFq3oplNurfvtyXKDguddO"
    },
    {
      "folder": "45",
      "filename": "24622741.jpg",
      "externalId": "1Q5qC2JgXd_MTCQ1iqwxAVhnmXYhGHExi"
    }
  ],
  "setlist": [
    {
      "order": 1,
      "song": "Quietly",
      "feat": "",
      "note": "",
      "comment": "",
      "coverOf": ""
    },
    {
      "order": 2,
      "song": "Oh What A Night",
      "feat": "",
      "note": "",
      "comment": "",
      "coverOf": ""
    },
    {
      "order": 3,
      "song": "You Can't Stop Me",
      "feat": "",
      "note": "",
      "comment": "",
      "coverOf": ""
    },
    {
      "order": 4,
      "song": "Open Your Eyes",
      "feat": "",
      "note": "",
      "comment": "",
      "coverOf": ""
    },
    {
      "order": 5,
      "song": "Sunday Lover",
      "feat": "",
      "note": "",
      "comment": "",
      "coverOf": ""
    },
    {
      "order": 6,
      "song": "Pretty In Scarlet",
      "feat": "",
      "note": "",
      "comment": "",
      "coverOf": ""
    },
    {
      "order": 7,
      "song": "Fire In Your Eyes",
      "feat": "",
      "note": "",
      "comment": "",
      "coverOf": ""
    },
    {
      "order": 8,
      "song": "She's A Killer",
      "feat": "",
      "note": "",
      "comment": "",
      "coverOf": ""
    },
    {
      "order": 9,
      "song": "Tiger",
      "feat": "",
      "note": "",
      "comment": "",
      "coverOf": ""
    },
    {
      "order": 10,
      "song": "All I Wanna Do",
      "feat": "",
      "note": "",
      "comment": "",
      "coverOf": ""
    },
    {
      "order": 11,
      "song": "When The Ships Arrive",
      "feat": "",
      "note": "",
      "comment": "",
      "coverOf": ""
    },
    {
      "order": 12,
      "song": "Fanman",
      "feat": "",
      "note": "",
      "comment": "",
      "coverOf": ""
    },
    {
      "order": 13,
      "song": "Dick",
      "feat": "",
      "note": "",
      "comment": "",
      "coverOf": ""
    },
    {
      "order": 14,
      "song": "This Time",
      "feat": "",
      "note": "",
      "comment": "",
      "coverOf": ""
    },
    {
      "order": 15,
      "song": "Plastic Mouth (instrumental)",
      "feat": "",
      "note": "",
      "comment": "",
      "coverOf": ""
    },
    {
      "order": 16,
      "song": "Big In Japan",
      "feat": "",
      "note": "",
      "comment": "",
      "coverOf": ""
    },
    {
      "order": 17,
      "song": "Lords Of The Boards",
      "feat": "",
      "note": "",
      "comment": "",
      "coverOf": ""
    }
  ],
  "extras": []
}