{
  "originalTitle": "Judas Priest - 13.06.2004 - Oberhausen - Germany - Konig Pilsener Arena",
  "created": 1704067200,
  "lastUpdated": 1752181957,
  "bands": [
    "Judas Priest"
  ],
  "startDate": {
    "day": "13",
    "month": "06",
    "year": "2004"
  },
  "startDateUnix": 1087084800,
  "endDate": {
    "day": "13",
    "month": "06",
    "year": "2004"
  },
  "endDateUnix": 1087084800,
  "location": {
    "city": "Oberhausen",
    "state": "",
    "country": "Germany",
    "venue": "Konig Pilsener Arena",
    "event": ""
  },
  "tvChannel": "",
  "showName": "",
  "source": "",
  "category": [
    "video"
  ],
  "master": false,
  "public": true,
  "ownIdentifier": "HDD#C",
  "tradeLabel": "",
  "authoredBy": "",
  "transferredBy": "",
  "notes": "",
  "tapers": [],
  "specs": {
    "media": [
      {
        "type": "DVD-5",
        "size": 4.24,
        "unit": "Gb"
      }
    ],
    "chapters": true,
    "menu": true,
    "length": 5593,
    "video": [
      {
        "tvFormat": "PAL",
        "ratio": "4:3",
        "resolution": "720x576",
        "bitrateType": "VBR",
        "bitrateKbps": null,
        "fps": "",
        "standard": "",
        "codec": "",
        "letterboxed": false
      }
    ],
    "audio": [
      {
        "language": "en",
        "codec": "AC3",
        "rateHz": null,
        "bitrateKbps": null,
        "channels": 3
      }
    ],
    "sourceDetail": {
      "recordingType": "AMT",
      "sourceMediaType": "",
      "finalMediaType": "",
      "fileFormat": "DVD"
    }
  },
  "relatedShows": [],
  "childOf": "",
  "images": [
    {
      "folder": "13",
      "filename": "69630977.jpg",
      "externalId": "1SmmyrRMYqn24-m4H6jfNzDkRUMsNdlFB"
    },
    {
      "folder": "13",
      "filename": "34784348.jpg",
      "externalId": "1nc2vgt5JfXO_otxMQRAnn5xuOaUNo35A"
    },
    {
      "folder": "13",
      "filename": "55503620.jpg",
      "externalId": "1nbgGPs1tvXFADwj_NjYgKqmIxfMNZiEk"
    },
    {
      "folder": "13",
      "filename": "01792240.jpg",
      "externalId": "1FzcZ-jKJgrkEFzabP-u_UQsseLcjY83t"
    }
  ],
  "setlist": [
    {
      "order": 1,
      "song": "Hellion",
      "feat": "",
      "note": "",
      "comment": "",
      "coverOf": ""
    },
    {
      "order": 2,
      "song": "Electric Eye",
      "feat": "",
      "note": "",
      "comment": "",
      "coverOf": ""
    },
    {
      "order": 3,
      "song": "Metal Gods",
      "feat": "",
      "note": "",
      "comment": "",
      "coverOf": ""
    },
    {
      "order": 4,
      "song": "Heading Out To The Highway",
      "feat": "",
      "note": "",
      "comment": "",
      "coverOf": ""
    },
    {
      "order": 5,
      "song": "The Ripper",
      "feat": "",
      "note": "",
      "comment": "",
      "coverOf": ""
    },
    {
      "order": 6,
      "song": "A Touch Of Evil",
      "feat": "",
      "note": "",
      "comment": "",
      "coverOf": ""
    },
    {
      "order": 7,
      "song": "The Sentinel",
      "feat": "",
      "note": "",
      "comment": "",
      "coverOf": ""
    },
    {
      "order": 8,
      "song": "Turbo Lover",
      "feat": "",
      "note": "",
      "comment": "",
      "coverOf": ""
    },
    {
      "order": 9,
      "song": "Victim Of Changes",
      "feat": "",
      "note": "",
      "comment": "",
      "coverOf": ""
    },
    {
      "order": 10,
      "song": "Diamonds And Rust",
      "feat": "",
      "note": "",
      "comment": "",
      "coverOf": ""
    },
    {
      "order": 11,
      "song": "Breaking The Law",
      "feat": "",
      "note": "",
      "comment": "",
      "coverOf": ""
    },
    {
      "order": 12,
      "song": "Beyond The Realms Of Death",
      "feat": "",
      "note": "",
      "comment": "",
      "coverOf": ""
    },
    {
      "order": 13,
      "song": "The Green Manalishi",
      "feat": "",
      "note": "",
      "comment": "",
      "coverOf": ""
    },
    {
      "order": 14,
      "song": "Painkiller",
      "feat": "",
      "note": "",
      "comment": "",
      "coverOf": ""
    },
    {
      "order": 15,
      "song": "Hell Bent For Leather",
      "feat": "",
      "note": "",
      "comment": "",
      "coverOf": ""
    },
    {
      "order": 16,
      "song": "Living After Midnight",
      "feat": "",
      "note": "",
      "comment": "",
      "coverOf": ""
    },
    {
      "order": 17,
      "song": "United",
      "feat": "",
      "note": "",
      "comment": "",
      "coverOf": ""
    },
    {
      "order": 18,
      "song": "Your've Got Another Thing Comin'",
      "feat": "",
      "note": "",
      "comment": "",
      "coverOf": ""
    }
  ],
  "extras": []
}