{
  "originalTitle": "Metallica - 22.07.1994 - Mountain View - CA - USA - Shoreline Amphitheatre (Source 2)",
  "created": 1704067200,
  "lastUpdated": 1765143448,
  "bands": [
    "Metallica"
  ],
  "startDate": {
    "day": "22",
    "month": "07",
    "year": "1994"
  },
  "startDateUnix": 774835200,
  "endDate": {
    "day": "22",
    "month": "07",
    "year": "1994"
  },
  "endDateUnix": 774835200,
  "location": {
    "city": "Mountain View",
    "state": "CA",
    "country": "USA",
    "venue": "Shoreline Amphitheatre",
    "event": ""
  },
  "tvChannel": "",
  "showName": "",
  "source": "Source 2",
  "category": [
    "video"
  ],
  "master": false,
  "public": true,
  "ownIdentifier": "HDD#A",
  "tradeLabel": "",
  "authoredBy": "",
  "transferredBy": "Bellower",
  "notes": "",
  "tapers": [],
  "specs": {
    "media": [
      {
        "type": "DVD-9",
        "size": 7.64,
        "unit": "Gb"
      }
    ],
    "chapters": true,
    "menu": true,
    "length": 8253,
    "video": [
      {
        "tvFormat": "NTSC",
        "ratio": "4:3",
        "resolution": "720x480",
        "bitrateType": "VBR",
        "bitrateKbps": null,
        "fps": "",
        "standard": "",
        "codec": "",
        "letterboxed": false
      }
    ],
    "audio": [
      {
        "language": "",
        "codec": "AC3",
        "rateHz": null,
        "bitrateKbps": null,
        "channels": 2
      }
    ],
    "sourceDetail": {
      "recordingType": "PRO",
      "sourceMediaType": "",
      "finalMediaType": "",
      "fileFormat": "DVD"
    }
  },
  "relatedShows": [],
  "childOf": "",
  "images": [
    {
      "folder": "74",
      "filename": "40080194.jpg",
      "externalId": "1L-0aeLzIM7X1ndfP_RrDVUDaYIdzkrGq"
    },
    {
      "folder": "74",
      "filename": "87515968.jpg",
      "externalId": "10pjIDKIzQbpM-txGkSfk_Kkn3FRh4QwA"
    },
    {
      "folder": "74",
      "filename": "77928427.jpg",
      "externalId": "13c_AtnOztezVi4awlrrKIwCZfHCCC5RF"
    },
    {
      "folder": "74",
      "filename": "75926366.jpg",
      "externalId": "1tngQY-tVkkbi5uzI6aztIR195QWnsklo"
    }
  ],
  "setlist": [
    {
      "order": 1,
      "song": "Breadfan",
      "feat": "",
      "note": "",
      "comment": "",
      "coverOf": ""
    },
    {
      "order": 2,
      "song": "Master of Puppets",
      "feat": "",
      "note": "",
      "comment": "",
      "coverOf": ""
    },
    {
      "order": 3,
      "song": "Wherever I May Roam",
      "feat": "",
      "note": "",
      "comment": "",
      "coverOf": ""
    },
    {
      "order": 4,
      "song": "Harvester of Sorrow",
      "feat": "",
      "note": "",
      "comment": "",
      "coverOf": ""
    },
    {
      "order": 5,
      "song": "Welcome Home (Sanitarium)",
      "feat": "",
      "note": "",
      "comment": "",
      "coverOf": ""
    },
    {
      "order": 6,
      "song": "The God That Failed",
      "feat": "",
      "note": "",
      "comment": "",
      "coverOf": ""
    },
    {
      "order": 7,
      "song": "Ride The Lightning / No Remorse / The Four Horsemen / Phantom Lord / Fight Fire With Fire",
      "feat": "",
      "note": "",
      "comment": "",
      "coverOf": ""
    },
    {
      "order": 8,
      "song": "For Whom The Bell Tolls",
      "feat": "",
      "note": "",
      "comment": "",
      "coverOf": ""
    },
    {
      "order": 9,
      "song": "Disposable Heroes",
      "feat": "",
      "note": "",
      "comment": "",
      "coverOf": ""
    },
    {
      "order": 10,
      "song": "Seek and Destroy",
      "feat": "",
      "note": "",
      "comment": "",
      "coverOf": ""
    },
    {
      "order": 11,
      "song": "Guitar Solo",
      "feat": "",
      "note": "",
      "comment": "",
      "coverOf": ""
    },
    {
      "order": 12,
      "song": "Nothing Else Matters",
      "feat": "",
      "note": "",
      "comment": "",
      "coverOf": ""
    },
    {
      "order": 13,
      "song": "Creeping Death",
      "feat": "",
      "note": "",
      "comment": "",
      "coverOf": ""
    },
    {
      "order": 14,
      "song": "Bass Solo",
      "feat": "",
      "note": "",
      "comment": "",
      "coverOf": ""
    },
    {
      "order": 15,
      "song": "Fade to Black",
      "feat": "",
      "note": "",
      "comment": "",
      "coverOf": ""
    },
    {
      "order": 16,
      "song": "Whiplash",
      "feat": "",
      "note": "",
      "comment": "",
      "coverOf": ""
    },
    {
      "order": 17,
      "song": "Sad But True",
      "feat": "",
      "note": "",
      "comment": "",
      "coverOf": ""
    },
    {
      "order": 18,
      "song": "One",
      "feat": "",
      "note": "",
      "comment": "",
      "coverOf": ""
    },
    {
      "order": 19,
      "song": "Enter Sandman",
      "feat": "",
      "note": "",
      "comment": "",
      "coverOf": ""
    },
    {
      "order": 20,
      "song": "So What",
      "feat": "",
      "note": "",
      "comment": "",
      "coverOf": "Anti-Nowhere League"
    }
  ],
  "extras": []
}