{
  "originalTitle": "Nightwish - 18.04.2015 - Chicago - IL - USA - Concord Music Hall",
  "created": 1704067200,
  "lastUpdated": 1752181957,
  "bands": [
    "Nightwish"
  ],
  "startDate": {
    "day": "18",
    "month": "04",
    "year": "2015"
  },
  "startDateUnix": 1429315200,
  "endDate": {
    "day": "18",
    "month": "04",
    "year": "2015"
  },
  "endDateUnix": 1429315200,
  "location": {
    "city": "Chicago",
    "state": "IL",
    "country": "USA",
    "venue": "Concord Music Hall",
    "event": ""
  },
  "tvChannel": "",
  "showName": "",
  "source": "",
  "category": [
    "video"
  ],
  "master": false,
  "public": true,
  "ownIdentifier": "HDD#J",
  "tradeLabel": "",
  "authoredBy": "",
  "transferredBy": "",
  "notes": "",
  "tapers": [],
  "specs": {
    "media": [
      {
        "type": "BD-25",
        "size": 21.1,
        "unit": "Gb"
      }
    ],
    "chapters": true,
    "menu": true,
    "length": 6480,
    "video": [
      {
        "tvFormat": "",
        "ratio": "",
        "resolution": "1920x1080",
        "bitrateType": "",
        "bitrateKbps": null,
        "fps": "29.97",
        "standard": "MPEG2",
        "codec": "",
        "letterboxed": false
      }
    ],
    "audio": [
      {
        "language": "",
        "codec": "PCM",
        "rateHz": 48000,
        "bitrateKbps": 1536,
        "channels": 2
      }
    ],
    "sourceDetail": {
      "recordingType": "AMT",
      "sourceMediaType": "Digicam",
      "finalMediaType": "HD",
      "fileFormat": "M2TS"
    }
  },
  "relatedShows": [],
  "childOf": "",
  "images": [
    {
      "folder": "64",
      "filename": "79268504.jpg",
      "externalId": "1V5C3A8krcA2qgbD4MfTa5m5hyTSqtnKp"
    },
    {
      "folder": "64",
      "filename": "78519734.jpg",
      "externalId": "12FttN0_AR4yTaw1aaIepGOpgGld7u2xs"
    },
    {
      "folder": "64",
      "filename": "23411802.jpg",
      "externalId": "1yiv3oE6AivRCg-KIYcPM23DLz8WStYHD"
    },
    {
      "folder": "64",
      "filename": "10746549.jpg",
      "externalId": "15ypBoXfThdUL7SAEI0Q-lY2ERq8YK45r"
    }
  ],
  "setlist": [
    {
      "order": 1,
      "song": "Shudder Before The Beautiful",
      "feat": "",
      "note": "",
      "comment": "",
      "coverOf": ""
    },
    {
      "order": 2,
      "song": "Yours Is An Empty Hope",
      "feat": "",
      "note": "",
      "comment": "",
      "coverOf": ""
    },
    {
      "order": 3,
      "song": "Amaranth",
      "feat": "",
      "note": "",
      "comment": "",
      "coverOf": ""
    },
    {
      "order": 4,
      "song": "She Is My Sin",
      "feat": "",
      "note": "",
      "comment": "",
      "coverOf": ""
    },
    {
      "order": 5,
      "song": "Endless Forms Most Beautiful",
      "feat": "",
      "note": "",
      "comment": "",
      "coverOf": ""
    },
    {
      "order": 6,
      "song": "My Walden",
      "feat": "",
      "note": "",
      "comment": "",
      "coverOf": ""
    },
    {
      "order": 7,
      "song": "The Islander",
      "feat": "",
      "note": "",
      "comment": "",
      "coverOf": ""
    },
    {
      "order": 8,
      "song": "Elan",
      "feat": "",
      "note": "",
      "comment": "",
      "coverOf": ""
    },
    {
      "order": 9,
      "song": "Weak Fantasy",
      "feat": "",
      "note": "",
      "comment": "",
      "coverOf": ""
    },
    {
      "order": 10,
      "song": "Storytime",
      "feat": "",
      "note": "",
      "comment": "",
      "coverOf": ""
    },
    {
      "order": 11,
      "song": "Ever Dream",
      "feat": "",
      "note": "",
      "comment": "",
      "coverOf": ""
    },
    {
      "order": 12,
      "song": "I Want My Tears Back",
      "feat": "",
      "note": "",
      "comment": "",
      "coverOf": ""
    },
    {
      "order": 13,
      "song": "Stargazers",
      "feat": "",
      "note": "",
      "comment": "",
      "coverOf": ""
    },
    {
      "order": 14,
      "song": "Sleeping Sun",
      "feat": "",
      "note": "",
      "comment": "",
      "coverOf": ""
    },
    {
      "order": 15,
      "song": "The Greatest Show On Earth",
      "feat": "",
      "note": "",
      "comment": "",
      "coverOf": ""
    },
    {
      "order": 16,
      "song": "Ghost Love Score",
      "feat": "",
      "note": "",
      "comment": "",
      "coverOf": ""
    },
    {
      "order": 17,
      "song": "Last Ride Of The Day",
      "feat": "",
      "note": "",
      "comment": "",
      "coverOf": ""
    }
  ],
  "extras": []
}