{
  "originalTitle": "Nirvana - 23.06.1989 - Westwood - CA - USA - Rhino Records [AUDIO]",
  "created": 1704067200,
  "lastUpdated": 1752181957,
  "bands": [
    "Nirvana"
  ],
  "startDate": {
    "day": "23",
    "month": "06",
    "year": "1989"
  },
  "startDateUnix": 614563200,
  "endDate": {
    "day": "23",
    "month": "06",
    "year": "1989"
  },
  "endDateUnix": 614563200,
  "location": {
    "city": "Westwood",
    "state": "CA",
    "country": "USA",
    "venue": "Rhino Records",
    "event": ""
  },
  "tvChannel": "",
  "showName": "",
  "source": "",
  "category": [
    "audio"
  ],
  "master": false,
  "public": true,
  "ownIdentifier": "HDD#F",
  "tradeLabel": "",
  "authoredBy": "",
  "transferredBy": "Kris Sproul",
  "notes": "AMT#2a. JVC HR-S9911U > Echo Layla24 > Adobe Audition 1.5 > CD Wave 1.94.8 > FLAC frontend 1.7.1.",
  "tapers": [],
  "specs": {
    "media": [
      {
        "type": "CD",
        "size": 102,
        "unit": "Mb"
      }
    ],
    "chapters": false,
    "menu": false,
    "length": 1072,
    "video": {
      "format": "",
      "ratio": "",
      "resolution": "",
      "bitrateType": "",
      "bitrateKbps": null,
      "letterboxed": false
    },
    "audio": [
      {
        "language": "",
        "codec": "PCM",
        "rateHz": 44100,
        "bitrateKbps": 1411,
        "channels": 2
      }
    ],
    "sourceDetail": {
      "recordingType": "AMT",
      "sourceMediaType": "",
      "finalMediaType": "",
      "fileFormat": "FLAC"
    }
  },
  "relatedShows": [],
  "childOf": "",
  "images": [],
  "setlist": [
    {
      "order": 1,
      "song": "Love Buzz",
      "feat": "",
      "note": "incomplete",
      "comment": "",
      "coverOf": ""
    },
    {
      "order": 2,
      "song": "Big Cheese",
      "feat": "",
      "note": "incomplete",
      "comment": "",
      "coverOf": ""
    },
    {
      "order": 3,
      "song": "About A Girl",
      "feat": "",
      "note": "incomplete",
      "comment": "",
      "coverOf": ""
    },
    {
      "order": 4,
      "song": "Sifting",
      "feat": "",
      "note": "incomplete",
      "comment": "",
      "coverOf": ""
    },
    {
      "order": 5,
      "song": "Spank Thru",
      "feat": "",
      "note": "incomplete",
      "comment": "",
      "coverOf": ""
    },
    {
      "order": 6,
      "song": "Dive",
      "feat": "",
      "note": "incomplete",
      "comment": "",
      "coverOf": ""
    }
  ],
  "extras": []
}