{
  "originalTitle": "No Doubt - 20.03.1997 - Stockholm - Sweden - Solnahallen",
  "created": 1704067200,
  "lastUpdated": 1752181957,
  "bands": [
    "No Doubt"
  ],
  "startDate": {
    "day": "20",
    "month": "03",
    "year": "1997"
  },
  "startDateUnix": 858816000,
  "endDate": {
    "day": "20",
    "month": "03",
    "year": "1997"
  },
  "endDateUnix": 858816000,
  "location": {
    "city": "Stockholm",
    "state": "",
    "country": "Sweden",
    "venue": "Solnahallen",
    "event": ""
  },
  "tvChannel": "",
  "showName": "",
  "source": "",
  "category": [
    "video"
  ],
  "master": false,
  "public": true,
  "ownIdentifier": "HDD#F",
  "tradeLabel": "",
  "authoredBy": "",
  "transferredBy": "",
  "notes": "",
  "tapers": [],
  "specs": {
    "media": [
      {
        "type": "DVD-5",
        "size": 3.87,
        "unit": "Gb"
      }
    ],
    "chapters": true,
    "menu": true,
    "length": 3400,
    "video": [
      {
        "tvFormat": "PAL",
        "ratio": "4:3",
        "resolution": "720x576",
        "bitrateType": "VBR",
        "bitrateKbps": null,
        "fps": "",
        "standard": "",
        "codec": "",
        "letterboxed": false
      }
    ],
    "audio": [
      {
        "language": "",
        "codec": "LPCM",
        "rateHz": null,
        "bitrateKbps": null,
        "channels": 2
      }
    ],
    "sourceDetail": {
      "recordingType": "PRO",
      "sourceMediaType": "VHS",
      "finalMediaType": "",
      "fileFormat": "DVD"
    }
  },
  "relatedShows": [],
  "childOf": "",
  "images": [
    {
      "folder": "32",
      "filename": "05292787.jpg",
      "externalId": "1-juoosrrHOX3tbbn9j518EJeLNhiIwOZ"
    },
    {
      "folder": "32",
      "filename": "50409206.jpg",
      "externalId": "1CNnmpRuzng9I82CjtbUAKsjgkgW4qQFU"
    },
    {
      "folder": "32",
      "filename": "58665053.jpg",
      "externalId": "1oeM3xe3sotW3wgaX0WaAWpiZ31bWnVWH"
    },
    {
      "folder": "32",
      "filename": "31119466.jpg",
      "externalId": "1Ws_CSqJCsw9z9a2hUe1DuS7nNx8dJpC4"
    }
  ],
  "setlist": [
    {
      "order": 1,
      "song": "Different People",
      "feat": "",
      "note": "",
      "comment": "",
      "coverOf": ""
    },
    {
      "order": 2,
      "song": "Just A Girl",
      "feat": "",
      "note": "",
      "comment": "",
      "coverOf": ""
    },
    {
      "order": 3,
      "song": "Interview",
      "feat": "",
      "note": "",
      "comment": "",
      "coverOf": ""
    },
    {
      "order": 4,
      "song": "The Climb",
      "feat": "",
      "note": "",
      "comment": "",
      "coverOf": ""
    },
    {
      "order": 5,
      "song": "Sunday Morning",
      "feat": "",
      "note": "",
      "comment": "",
      "coverOf": ""
    },
    {
      "order": 6,
      "song": "Interview",
      "feat": "",
      "note": "",
      "comment": "",
      "coverOf": ""
    },
    {
      "order": 7,
      "song": "Move On",
      "feat": "",
      "note": "",
      "comment": "",
      "coverOf": ""
    },
    {
      "order": 8,
      "song": "You Can Do It",
      "feat": "",
      "note": "",
      "comment": "",
      "coverOf": ""
    },
    {
      "order": 9,
      "song": "Interview",
      "feat": "",
      "note": "",
      "comment": "",
      "coverOf": ""
    },
    {
      "order": 10,
      "song": "Don't Speak",
      "feat": "",
      "note": "",
      "comment": "",
      "coverOf": ""
    },
    {
      "order": 11,
      "song": "Spiderwebs",
      "feat": "",
      "note": "",
      "comment": "",
      "coverOf": ""
    }
  ],
  "extras": []
}