{
  "originalTitle": "Sepultura - 17.12.1990 - El Paso - TX - USA - County Coliseum",
  "created": 1704067200,
  "lastUpdated": 1752181957,
  "bands": [
    "Sepultura"
  ],
  "startDate": {
    "day": "17",
    "month": "12",
    "year": "1990"
  },
  "startDateUnix": 661392000,
  "endDate": {
    "day": "17",
    "month": "12",
    "year": "1990"
  },
  "endDateUnix": 661392000,
  "location": {
    "city": "El Paso",
    "state": "TX",
    "country": "USA",
    "venue": "County Coliseum",
    "event": ""
  },
  "tvChannel": "",
  "showName": "",
  "source": "",
  "category": [
    "video"
  ],
  "master": false,
  "public": true,
  "ownIdentifier": "HDD#O",
  "tradeLabel": "",
  "authoredBy": "",
  "transferredBy": "",
  "notes": "",
  "tapers": [],
  "specs": {
    "media": [
      {
        "type": "DVD-5",
        "size": 3.37,
        "unit": "Gb"
      }
    ],
    "chapters": true,
    "menu": true,
    "length": 3599,
    "video": [
      {
        "tvFormat": "NTSC",
        "ratio": "4:3",
        "resolution": "720x480",
        "bitrateType": "VBR",
        "bitrateKbps": null,
        "fps": "",
        "standard": "",
        "codec": "",
        "letterboxed": false
      }
    ],
    "audio": [
      {
        "language": "",
        "codec": "LPCM",
        "rateHz": null,
        "bitrateKbps": null,
        "channels": 2
      }
    ],
    "sourceDetail": {
      "recordingType": "AMT",
      "sourceMediaType": "VHS",
      "finalMediaType": "",
      "fileFormat": "DVD"
    }
  },
  "relatedShows": [],
  "childOf": "",
  "images": [
    {
      "folder": "1",
      "filename": "47048.jpg",
      "externalId": "1bMwRF7W7hCB9b_A4mQNb9tGatTtqe25V"
    },
    {
      "folder": "1",
      "filename": "17492.jpg",
      "externalId": "1nle7_KYBqM8t3loVIQWXFCJBllfAPFHD"
    },
    {
      "folder": "1",
      "filename": "33861.jpg",
      "externalId": "1udUapsRPEWubqXcr_udprm2SAj6XPWJE"
    },
    {
      "folder": "1",
      "filename": "46067.jpg",
      "externalId": "1gLJVD9MizL808iLfzz2VnzqtWYoZ4cXh"
    },
    {
      "folder": "1",
      "filename": "22537.jpg",
      "externalId": "1VSQongh-P8N90Vge-klXM_XcQZsD7ZBi"
    },
    {
      "folder": "1",
      "filename": "78974.jpg",
      "externalId": "1_YqUriA8iB1PL7SFd7yM2YNUsD7nmuBz"
    },
    {
      "folder": "1",
      "filename": "52126.jpg",
      "externalId": "1XojgzQgoRepJ6ZdLpL1vJww3ct3VfZIX"
    },
    {
      "folder": "1",
      "filename": "98401.jpg",
      "externalId": "1m-fYy8iwHATQXgmOVrZDFkbfBJES_-gW"
    }
  ],
  "setlist": [
    {
      "order": 1,
      "song": "Primitive Future",
      "feat": "",
      "note": "",
      "comment": "",
      "coverOf": ""
    },
    {
      "order": 2,
      "song": "Inner Self",
      "feat": "",
      "note": "",
      "comment": "",
      "coverOf": ""
    },
    {
      "order": 3,
      "song": "Mass Hypnosis",
      "feat": "",
      "note": "",
      "comment": "",
      "coverOf": ""
    },
    {
      "order": 4,
      "song": "Troops Of Doom",
      "feat": "",
      "note": "",
      "comment": "",
      "coverOf": ""
    },
    {
      "order": 5,
      "song": "Stronger Then Hate",
      "feat": "",
      "note": "",
      "comment": "",
      "coverOf": ""
    },
    {
      "order": 6,
      "song": "Slaves Of Pain",
      "feat": "",
      "note": "",
      "comment": "",
      "coverOf": ""
    },
    {
      "order": 7,
      "song": "Orgasmatron",
      "feat": "",
      "note": "",
      "comment": "",
      "coverOf": ""
    },
    {
      "order": 8,
      "song": "Break",
      "feat": "",
      "note": "",
      "comment": "",
      "coverOf": ""
    },
    {
      "order": 9,
      "song": "Escape To The Void",
      "feat": "",
      "note": "",
      "comment": "",
      "coverOf": ""
    },
    {
      "order": 10,
      "song": "Antichrist",
      "feat": "",
      "note": "",
      "comment": "",
      "coverOf": ""
    },
    {
      "order": 11,
      "song": "Murder",
      "feat": "",
      "note": "",
      "comment": "",
      "coverOf": ""
    },
    {
      "order": 12,
      "song": "Sarcastic Existance",
      "feat": "",
      "note": "",
      "comment": "",
      "coverOf": ""
    },
    {
      "order": 13,
      "song": "Symptom Of The Universe",
      "feat": "",
      "note": "",
      "comment": "",
      "coverOf": ""
    },
    {
      "order": 14,
      "song": "Policia",
      "feat": "",
      "note": "",
      "comment": "",
      "coverOf": ""
    },
    {
      "order": 15,
      "song": "Beneath The Remains",
      "feat": "",
      "note": "",
      "comment": "",
      "coverOf": ""
    }
  ],
  "extras": []
}