{
  "originalTitle": "Sepultura - 30.04.1994 - Buenos Aires - Argentina - Estadio Obras Sanitarias [AUDIO]",
  "created": 1704067200,
  "lastUpdated": 1752181957,
  "bands": [
    "Sepultura"
  ],
  "startDate": {
    "day": "30",
    "month": "04",
    "year": "1994"
  },
  "startDateUnix": 767664000,
  "endDate": {
    "day": "30",
    "month": "04",
    "year": "1994"
  },
  "endDateUnix": 767664000,
  "location": {
    "city": "Buenos Aires",
    "state": "",
    "country": "Argentina",
    "venue": "Estadio Obras Sanitarias",
    "event": ""
  },
  "tvChannel": "",
  "showName": "",
  "source": "",
  "category": [
    "audio"
  ],
  "master": false,
  "public": true,
  "ownIdentifier": "HDD#D",
  "tradeLabel": "",
  "authoredBy": "",
  "transferredBy": "",
  "notes": "Original Silver CD > Easy CD-DA Extractor 10 > FLAC (level 8).",
  "tapers": [],
  "specs": {
    "media": [
      {
        "type": "CD",
        "size": 473,
        "unit": "Mb"
      }
    ],
    "chapters": false,
    "menu": false,
    "length": 4370,
    "video": {
      "format": "",
      "ratio": "",
      "resolution": "",
      "bitrateType": "",
      "bitrateKbps": null,
      "letterboxed": false
    },
    "audio": [
      {
        "language": "",
        "codec": "FLAC",
        "rateHz": 44100,
        "bitrateKbps": 1411,
        "channels": 2
      }
    ],
    "sourceDetail": {
      "recordingType": "AMT",
      "sourceMediaType": "",
      "finalMediaType": "",
      "fileFormat": "FLAC"
    }
  },
  "relatedShows": [],
  "childOf": "",
  "images": [],
  "setlist": [
    {
      "order": 1,
      "song": "Refuse/Resist",
      "feat": "",
      "note": "",
      "comment": "",
      "coverOf": ""
    },
    {
      "order": 2,
      "song": "Slave New World",
      "feat": "",
      "note": "",
      "comment": "",
      "coverOf": ""
    },
    {
      "order": 3,
      "song": "Troops Of Doom",
      "feat": "",
      "note": "",
      "comment": "",
      "coverOf": ""
    },
    {
      "order": 4,
      "song": "Propaganda",
      "feat": "",
      "note": "",
      "comment": "",
      "coverOf": ""
    },
    {
      "order": 5,
      "song": "Crucifixion",
      "feat": "",
      "note": "",
      "comment": "",
      "coverOf": ""
    },
    {
      "order": 6,
      "song": "Beneath The Remains",
      "feat": "",
      "note": "",
      "comment": "",
      "coverOf": ""
    },
    {
      "order": 7,
      "song": "Escape To The Void",
      "feat": "",
      "note": "",
      "comment": "",
      "coverOf": ""
    },
    {
      "order": 8,
      "song": "Inner Self",
      "feat": "",
      "note": "",
      "comment": "",
      "coverOf": ""
    },
    {
      "order": 9,
      "song": "Manifest",
      "feat": "",
      "note": "",
      "comment": "",
      "coverOf": ""
    },
    {
      "order": 10,
      "song": "Nomad",
      "feat": "",
      "note": "",
      "comment": "",
      "coverOf": ""
    },
    {
      "order": 11,
      "song": "Antichrist",
      "feat": "",
      "note": "",
      "comment": "",
      "coverOf": ""
    },
    {
      "order": 12,
      "song": "Desperate Cry",
      "feat": "",
      "note": "",
      "comment": "",
      "coverOf": ""
    },
    {
      "order": 13,
      "song": "Guitar Solo",
      "feat": "",
      "note": "",
      "comment": "",
      "coverOf": ""
    },
    {
      "order": 14,
      "song": "Kaiowas",
      "feat": "",
      "note": "",
      "comment": "",
      "coverOf": ""
    },
    {
      "order": 15,
      "song": "Altered State",
      "feat": "",
      "note": "",
      "comment": "",
      "coverOf": ""
    },
    {
      "order": 16,
      "song": "Biotech Is Godzilla",
      "feat": "",
      "note": "",
      "comment": "",
      "coverOf": ""
    },
    {
      "order": 17,
      "song": "Dead Embryonic Cells",
      "feat": "",
      "note": "",
      "comment": "",
      "coverOf": ""
    },
    {
      "order": 18,
      "song": "Arise",
      "feat": "",
      "note": "",
      "comment": "",
      "coverOf": ""
    },
    {
      "order": 19,
      "song": "Territory",
      "feat": "",
      "note": "",
      "comment": "",
      "coverOf": ""
    },
    {
      "order": 20,
      "song": "Crucificados Pelo Sistema",
      "feat": "",
      "note": "",
      "comment": "",
      "coverOf": "Ratos De Porao"
    },
    {
      "order": 21,
      "song": "Policia",
      "feat": "",
      "note": "",
      "comment": "",
      "coverOf": "Titas"
    },
    {
      "order": 22,
      "song": "Orgasmatron",
      "feat": "",
      "note": "",
      "comment": "",
      "coverOf": "Motorhead"
    },
    {
      "order": 23,
      "song": "Symptom Of The Universe",
      "feat": "",
      "note": "",
      "comment": "",
      "coverOf": "Black Sabbath"
    }
  ],
  "extras": []
}