{
  "originalTitle": "The Dillinger Escape Plan - 10.02.2010 - Paris - France - La Maroquinerie (Source 1)",
  "created": 1704067200,
  "lastUpdated": 1752181957,
  "bands": [
    "The Dillinger Escape Plan"
  ],
  "startDate": {
    "day": "10",
    "month": "02",
    "year": "2010"
  },
  "startDateUnix": 1265760000,
  "endDate": {
    "day": "10",
    "month": "02",
    "year": "2010"
  },
  "endDateUnix": 1265760000,
  "location": {
    "city": "Paris",
    "state": "",
    "country": "France",
    "venue": "La Maroquinerie",
    "event": ""
  },
  "tvChannel": "",
  "showName": "",
  "source": "Source 1",
  "category": [
    "video"
  ],
  "master": false,
  "public": true,
  "ownIdentifier": "HDD#O",
  "tradeLabel": "",
  "authoredBy": "",
  "transferredBy": "",
  "notes": "Amazing 4 cam mix!",
  "tapers": [
    "Sgt",
    "Comyoucom66",
    "Yohann",
    "Anaconda"
  ],
  "specs": {
    "media": [
      {
        "type": "DVD-5",
        "size": 3.93,
        "unit": "Gb"
      }
    ],
    "chapters": true,
    "menu": true,
    "length": 4449,
    "video": [
      {
        "tvFormat": "PAL",
        "ratio": "16:9",
        "resolution": "720x576",
        "bitrateType": "VBR",
        "bitrateKbps": null,
        "fps": "",
        "standard": "",
        "codec": "",
        "letterboxed": true
      }
    ],
    "audio": [
      {
        "language": "",
        "codec": "AC3",
        "rateHz": null,
        "bitrateKbps": null,
        "channels": 5
      }
    ],
    "sourceDetail": {
      "recordingType": "AMT",
      "sourceMediaType": "",
      "finalMediaType": "",
      "fileFormat": "DVD"
    }
  },
  "relatedShows": [],
  "childOf": "",
  "images": [
    {
      "folder": "20",
      "filename": "34681261.jpg",
      "externalId": "1YY8l7Q6oxU6SttQWPjRZOblSGsneq4IZ"
    },
    {
      "folder": "20",
      "filename": "91476206.jpg",
      "externalId": "1bpxRLKaapJ2fUzvcn28VbI8a-7l3qbGm"
    },
    {
      "folder": "20",
      "filename": "85776141.jpg",
      "externalId": "1A44fWZUINb7gUF8wYjGfXBIwKshK5nao"
    },
    {
      "folder": "20",
      "filename": "89762127.jpg",
      "externalId": "1xLFj0PID2Nrlw8WDAfev-IOuAu7UL0DR"
    }
  ],
  "setlist": [
    {
      "order": 1,
      "song": "Good Neighbor",
      "feat": "",
      "note": "",
      "comment": "",
      "coverOf": ""
    },
    {
      "order": 2,
      "song": "Panasonic Youth",
      "feat": "",
      "note": "",
      "comment": "",
      "coverOf": ""
    },
    {
      "order": 3,
      "song": "Fix Your Face",
      "feat": "",
      "note": "",
      "comment": "",
      "coverOf": ""
    },
    {
      "order": 4,
      "song": "Milk Lizard",
      "feat": "",
      "note": "",
      "comment": "",
      "coverOf": ""
    },
    {
      "order": 5,
      "song": "Sugar Coated Sour",
      "feat": "",
      "note": "",
      "comment": "",
      "coverOf": ""
    },
    {
      "order": 6,
      "song": "Chinses Whispers",
      "feat": "",
      "note": "",
      "comment": "",
      "coverOf": ""
    },
    {
      "order": 7,
      "song": "When Good Dogs Do Bad Things",
      "feat": "",
      "note": "",
      "comment": "",
      "coverOf": ""
    },
    {
      "order": 8,
      "song": "Moth Of Gosts",
      "feat": "",
      "note": "",
      "comment": "",
      "coverOf": ""
    },
    {
      "order": 9,
      "song": "Black Bubblegum",
      "feat": "",
      "note": "",
      "comment": "",
      "coverOf": ""
    },
    {
      "order": 10,
      "song": "Sunshine The Werewolf",
      "feat": "",
      "note": "",
      "comment": "",
      "coverOf": ""
    },
    {
      "order": 11,
      "song": "Horse Hunter",
      "feat": "",
      "note": "",
      "comment": "",
      "coverOf": ""
    },
    {
      "order": 12,
      "song": "Weekend Sex Change",
      "feat": "",
      "note": "",
      "comment": "",
      "coverOf": ""
    },
    {
      "order": 13,
      "song": "Lurch",
      "feat": "",
      "note": "",
      "comment": "",
      "coverOf": ""
    },
    {
      "order": 14,
      "song": "Farewell, Mona Lisa",
      "feat": "",
      "note": "",
      "comment": "",
      "coverOf": ""
    },
    {
      "order": 15,
      "song": "Head Over Hill",
      "feat": "",
      "note": "",
      "comment": "",
      "coverOf": "Fears For Fears"
    },
    {
      "order": 16,
      "song": "The Running Board",
      "feat": "",
      "note": "",
      "comment": "",
      "coverOf": ""
    },
    {
      "order": 17,
      "song": "43% Burnt",
      "feat": "",
      "note": "",
      "comment": "",
      "coverOf": ""
    }
  ],
  "extras": []
}