{
  "originalTitle": "Взрыв Кабачка В Коляске С Поносом - 14.01.2012 - Moscow - Russia - Plan B Club",
  "created": 1704067200,
  "lastUpdated": 1752181957,
  "bands": [
    "Взрыв Кабачка В Коляске С Поносом"
  ],
  "startDate": {
    "day": "14",
    "month": "01",
    "year": "2012"
  },
  "startDateUnix": 1326499200,
  "endDate": {
    "day": "14",
    "month": "01",
    "year": "2012"
  },
  "endDateUnix": 1326499200,
  "location": {
    "city": "Moscow",
    "state": "",
    "country": "Russia",
    "venue": "Plan B Club",
    "event": ""
  },
  "tvChannel": "",
  "showName": "",
  "source": "",
  "category": [
    "video"
  ],
  "master": false,
  "public": true,
  "ownIdentifier": "",
  "tradeLabel": "",
  "authoredBy": "",
  "transferredBy": "",
  "notes": "",
  "tapers": [],
  "specs": {
    "media": [
      {
        "type": "DVD-5",
        "size": 3,
        "unit": "Gb"
      }
    ],
    "chapters": false,
    "menu": false,
    "length": 1983,
    "video": [
      {
        "tvFormat": "",
        "ratio": "",
        "resolution": "1920x1080",
        "bitrateType": "",
        "bitrateKbps": null,
        "fps": "25.00",
        "standard": "MPEG4",
        "codec": "H264",
        "letterboxed": false
      }
    ],
    "audio": [
      {
        "language": "",
        "codec": "AC3",
        "rateHz": 48000,
        "bitrateKbps": null,
        "channels": 2
      }
    ],
    "sourceDetail": {
      "recordingType": "AMT",
      "sourceMediaType": "HD",
      "finalMediaType": "BD",
      "fileFormat": "M2TS"
    }
  },
  "relatedShows": [],
  "childOf": "",
  "images": [
    {
      "folder": "30",
      "filename": "82613600.jpg",
      "externalId": "1EaQETp8s19_c8FNLGD3A2UaUA96MlUO8"
    },
    {
      "folder": "30",
      "filename": "32344428.jpg",
      "externalId": "1NwHrjwlbigCBLHqS_L-xSlamdkRmu7V_"
    },
    {
      "folder": "30",
      "filename": "04927115.jpg",
      "externalId": "1VX_zHnsj03CxImgAyPeVb5lbHj_yYPLp"
    },
    {
      "folder": "30",
      "filename": "53671985.jpg",
      "externalId": "1xwM47Qb1-ta0wUkwmdsJS06IxYYNUUPR"
    }
  ],
  "setlist": []
}